core/__init__.py
core/config/__init__.py
core/config/defaults.yml
core/config/manager.py
core/config/sessions.py
core/utils/__init__.py
core/utils/csv.py
core/utils/dicts.py
core/utils/ftp.py
core/utils/json.py
core/utils/logging.py
core/utils/yaml.py
include_beer_core-1.0.0.dist-info/LICENSE
include_beer_core-1.0.0.dist-info/METADATA
include_beer_core-1.0.0.dist-info/WHEEL
include_beer_core-1.0.0.dist-info/top_level.txt
include_beer_core-1.0.0.dist-info/RECORD
