Metadata-Version: 2.1
Name: include-beer-core
Version: 1.0.0
Summary: Core modules for include-beer eco-system
Home-page: https://github.com/mbhein/include-beer-core
Author: Matthew Hein
Author-email: matthew.hein@gmail.com
License: MIT
Platform: UNKNOWN
Classifier: License :: OSI Approved :: MIT License
Classifier: Programming Language :: Python :: 3
Classifier: Programming Language :: Python :: 3.6
Classifier: Programming Language :: Python :: 3.7
Classifier: Programming Language :: Python :: 3.8
Requires-Dist: pyyaml
